{"O0aRPtA+isok6gw0VOa8Zw==":"mbr-1920x1305.jpg","f1GgzxQp8Xd44wlaXwFuXQ==":"fris-960x648.jpg","5sGrfcq9bNNtRpSiV1w/tg==":"mbr-1920x1280.jpg","vjUsYBoYHL4xAwZbc6lW/g==":"grey-arth-2000x1500.jpg","aANW+l7TyX62+vBglKLKrg==":"mbr-1920x1305.jpeg","3lfo/8zuSifW5aTCgUyHVQ==":"test-512x512.png","v5RfrhO2tWWBNKyCm8MjwQ==":"test(1)-256x256.png","acu0rcoeJz2pWvk0mMBpbQ==":"test(1)-1-256x256.png","shuU4BHa+VIt+PFidbisTA==":"ui-512x512.png","QvYCwmsklQO+E9uDSW1c9A==":"rust-512x512.jpg","LhepAFyQnou2Xw9nnnODfQ==":"virus-512x512.png","Z6HHyE0pjmgIXyceJrxlEQ==":"house-2000x1500.jpg","XEB+H21tfwvKedGpaHhLow==":"dark-clouds-2000x1125.jpg","B88zm1IDO1F0zS+URuMYGA==":"img_20200317-152207-1400x1050.jpg","aSg0mgGbva+HMjs1dilhOA==":"pis-1400x1050.jpg","/cTEPWme3cfowJ4nSkI6AA==":"img_20200317-153831-1400x1867.jpg","Yie4DM4/w2enbqduR0fvvQ==":"pi2-1400x1867.jpg","YAcGQCtqJMKnS/dH1700Tg==":"mbr-1-1920x1305.jpeg","S/rY7anTUAGO2T4shbWXBA==":"mbr-2-1920x1305.jpeg","22KpNG0xT3lwCfitpXbLcQ==":"pi2-1400x1867.jpeg","rdVyHFcUtrhJogME3t/9yg==":"pi2-1-1400x1867.jpeg","P47Np1upqveGI0usHsbFAg==":"pi2-2-1400x1867.jpeg"}